{
  "project_info": {
    "project_number": "21402723903",
    "firebase_url": "https://bounttylandapp.firebaseio.com",
    "project_id": "bounttylandapp",
    "storage_bucket": "bounttylandapp.appspot.com"
  },
  "client": [
    {
      "client_info": {
        "mobilesdk_app_id": "1:21402723903:android:d92a1758faf4c9b9",
        "android_client_info": {
          "package_name": "com.jajija.bountyland"
        }
      },
      "oauth_client": [
        {
          "client_id": "21402723903-o24men6s8ea2tepusapi4tm3riq3nhn6.apps.googleusercontent.com",
          "client_type": 3
        }
      ],
      "api_key": [
        {
          "current_key": "AIzaSyBjCv1bA4habanhX2BwY_ZsnBC_G3oJ6uc"
        }
      ],
      "services": {
        "analytics_service": {
          "status": 1
        },
        "appinvite_service": {
          "status": 1,
          "other_platform_oauth_client": []
        },
        "ads_service": {
          "status": 2
        }
      }
    }
  ],
  "configuration_version": "1"
}